main.py
agents/__init__.py
agents/analyzer_agent.py
agents/base_agent.py
agents/coordinator_agent.py
agents/formatter_agent.py
agents/processor_agent.py
agents/transcriber_agent.py
ai_agent_video_transcription-1.1.3.dist-info/licenses/AUTHORS.md
ai_agent_video_transcription-1.1.3.dist-info/licenses/LICENSE
cli/__init__.py
cli/interactive_cli.py
memory/__init__.py
memory/memory_manager.py
models/__init__.py
models/transcription_result.py
models/video_metadata.py
services/__init__.py
services/audio_service.py
services/output_service.py
services/transcription_service.py
services/video_service.py
utils/__init__.py
utils/async_helper.py
utils/config_loader.py
utils/file_handler.py
ai_agent_video_transcription-1.1.3.dist-info/METADATA
ai_agent_video_transcription-1.1.3.dist-info/WHEEL
ai_agent_video_transcription-1.1.3.dist-info/entry_points.txt
ai_agent_video_transcription-1.1.3.dist-info/top_level.txt
ai_agent_video_transcription-1.1.3.dist-info/RECORD
