Metadata-Version: 2.4
Name: ai-agent-video-transcription
Version: 1.1.3
Summary: Multi-agent AI system for video transcription using OpenAI Whisper, ChromaDB, and AutoGen
Home-page: https://github.com/lopand-solutions/video-transcription-agent
Author: Lopand Solutions
Author-email: Lopand Solutions <contact@lopand.com>
Maintainer: Paulo Cesar Andrade Gonzalez
Maintainer-email: Paulo Cesar Andrade Gonzalez <paulocesarandradegonzalez@lopand.com>
License: MIT
Project-URL: Homepage, https://github.com/lopand-solutions/video-transcription-agent
Project-URL: Documentation, https://github.com/lopand-solutions/video-transcription-agent#readme
Project-URL: Repository, https://github.com/lopand-solutions/video-transcription-agent.git
Project-URL: Issues, https://github.com/lopand-solutions/video-transcription-agent/issues
Project-URL: Changelog, https://github.com/lopand-solutions/video-transcription-agent/blob/main/CHANGELOG.md
Project-URL: Download, https://pypi.org/project/video-transcription-agent/#files
Project-URL: Source, https://github.com/lopand-solutions/video-transcription-agent
Keywords: video,transcription,ai,agents,whisper,chromadb,autogen,multimedia,speech-recognition,nlp,cli,machine-learning
Classifier: Development Status :: 4 - Beta
Classifier: Intended Audience :: Developers
Classifier: Intended Audience :: Science/Research
Classifier: Intended Audience :: End Users/Desktop
Classifier: License :: OSI Approved :: MIT License
Classifier: Operating System :: OS Independent
Classifier: Programming Language :: Python :: 3
Classifier: Programming Language :: Python :: 3.9
Classifier: Programming Language :: Python :: 3.10
Classifier: Programming Language :: Python :: 3.11
Classifier: Programming Language :: Python :: 3.12
Classifier: Programming Language :: Python :: 3.13
Classifier: Topic :: Scientific/Engineering :: Artificial Intelligence
Classifier: Topic :: Multimedia :: Video
Classifier: Topic :: Multimedia :: Sound/Audio :: Speech
Classifier: Topic :: Multimedia :: Sound/Audio :: Conversion
Classifier: Topic :: Software Development :: Libraries :: Python Modules
Classifier: Topic :: Text Processing :: Linguistic
Classifier: Environment :: Console
Classifier: Natural Language :: Spanish
Classifier: Natural Language :: English
Requires-Python: >=3.9
License-File: LICENSE
License-File: AUTHORS.md
Requires-Dist: langchain>=0.1.0
Requires-Dist: langchain-community>=0.0.20
Requires-Dist: langchain-openai>=0.0.6
Requires-Dist: pyautogen>=0.2.0
Requires-Dist: autogen-agentchat>=0.2.0
Requires-Dist: autogen>=0.9.0
Requires-Dist: chromadb>=0.4.15
Requires-Dist: openai-whisper>=20231117
Requires-Dist: ffmpeg-python>=0.2.0
Requires-Dist: pydub>=0.25.1
Requires-Dist: click>=8.1.7
Requires-Dist: PyYAML>=6.0.1
Requires-Dist: python-dotenv>=1.0.0
Requires-Dist: rich>=13.7.0
Requires-Dist: typing-extensions>=4.9.0
Requires-Dist: prompt-toolkit>=3.0.36
Requires-Dist: colorama>=0.4.6
Requires-Dist: questionary>=2.0.1
Provides-Extra: dev
Requires-Dist: pytest>=7.4.0; extra == "dev"
Requires-Dist: pytest-cov>=4.1.0; extra == "dev"
Requires-Dist: black>=23.12.0; extra == "dev"
Requires-Dist: flake8>=7.0.0; extra == "dev"
Requires-Dist: mypy>=1.8.0; extra == "dev"
Requires-Dist: pre-commit>=3.6.0; extra == "dev"
Requires-Dist: build>=0.10.0; extra == "dev"
Requires-Dist: twine>=4.0.0; extra == "dev"
Dynamic: author
Dynamic: home-page
Dynamic: license-file
Dynamic: maintainer
Dynamic: requires-python
